<?xml version="1.0" encoding="UTF-8"?>
<!-- IceNet-OS Openbox Configuration -->
<openbox_config xmlns="http://openbox.org/3.4/rc">

  <resistance>
    <strength>10</strength>
    <screen_edge_strength>20</screen_edge_strength>
  </resistance>

  <focus>
    <focusNew>yes</focusNew>
    <followMouse>no</followMouse>
    <focusLast>yes</focusLast>
    <underMouse>no</underMouse>
    <focusDelay>200</focusDelay>
    <raiseOnFocus>no</raiseOnFocus>
  </focus>

  <placement>
    <policy>Smart</policy>
    <center>yes</center>
    <monitor>Primary</monitor>
    <primaryMonitor>1</primaryMonitor>
  </placement>

  <theme>
    <name>IceNet-Dark</name>
    <titleLayout>NLIMC</titleLayout>
    <keepBorder>yes</keepBorder>
    <animateIconify>yes</animateIconify>
    <font place="ActiveWindow">
      <name>Sans</name>
      <size>10</size>
      <weight>Bold</weight>
      <slant>Normal</slant>
    </font>
    <font place="InactiveWindow">
      <name>Sans</name>
      <size>10</size>
      <weight>Normal</weight>
      <slant>Normal</slant>
    </font>
    <font place="MenuHeader">
      <name>Sans</name>
      <size>10</size>
      <weight>Bold</weight>
      <slant>Normal</slant>
    </font>
    <font place="MenuItem">
      <name>Sans</name>
      <size>10</size>
      <weight>Normal</weight>
      <slant>Normal</slant>
    </font>
  </theme>

  <desktops>
    <number>4</number>
    <firstdesk>1</firstdesk>
    <names>
      <name>Main</name>
      <name>Work</name>
      <name>Network</name>
      <name>System</name>
    </names>
    <popupTime>875</popupTime>
  </desktops>

  <resize>
    <drawContents>yes</drawContents>
    <popupShow>Nonpixel</popupShow>
    <popupPosition>Center</popupPosition>
    <popupFixedPosition>
      <x>10</x>
      <y>10</y>
    </popupFixedPosition>
  </resize>

  <margins>
    <top>0</top>
    <bottom>0</bottom>
    <left>0</left>
    <right>0</right>
  </margins>

  <dock>
    <position>TopLeft</position>
    <floatingX>0</floatingX>
    <floatingY>0</floatingY>
    <noStrut>no</noStrut>
    <stacking>Above</stacking>
    <direction>Vertical</direction>
    <autoHide>no</autoHide>
    <hideDelay>300</hideDelay>
    <showDelay>300</showDelay>
    <moveButton>Middle</moveButton>
  </dock>

  <keyboard>
    <chainQuitKey>C-g</chainQuitKey>

    <!-- Window management -->
    <keybind key="A-F4">
      <action name="Close"/>
    </keybind>
    <keybind key="A-Tab">
      <action name="NextWindow">
        <finalactions>
          <action name="Focus"/>
          <action name="Raise"/>
          <action name="Unshade"/>
        </finalactions>
      </action>
    </keybind>
    <keybind key="W-d">
      <action name="ToggleShowDesktop"/>
    </keybind>

    <!-- Window snapping -->
    <keybind key="W-Left">
      <action name="UnmaximizeFull"/>
      <action name="MoveResizeTo">
        <x>0</x>
        <y>0</y>
        <width>50%</width>
        <height>100%</height>
      </action>
    </keybind>
    <keybind key="W-Right">
      <action name="UnmaximizeFull"/>
      <action name="MoveResizeTo">
        <x>-0</x>
        <y>0</y>
        <width>50%</width>
        <height>100%</height>
      </action>
    </keybind>
    <keybind key="W-Up">
      <action name="Maximize"/>
    </keybind>

    <!-- Application launchers -->
    <keybind key="W-t">
      <action name="Execute">
        <command>lxterminal</command>
      </action>
    </keybind>
    <keybind key="W-e">
      <action name="Execute">
        <command>pcmanfm</command>
      </action>
    </keybind>
    <keybind key="W-r">
      <action name="Execute">
        <command>gmrun</command>
      </action>
    </keybind>
    <keybind key="W-l">
      <action name="Execute">
        <command>dm-tool lock</command>
      </action>
    </keybind>
    <keybind key="Print">
      <action name="Execute">
        <command>scrot</command>
      </action>
    </keybind>

    <!-- System control -->
    <keybind key="C-A-Delete">
      <action name="Execute">
        <command>lxtask</command>
      </action>
    </keybind>

  </keyboard>

  <mouse>
    <dragThreshold>8</dragThreshold>
    <doubleClickTime>200</doubleClickTime>
    <screenEdgeWarpTime>400</screenEdgeWarpTime>
    <screenEdgeWarpMouse>false</screenEdgeWarpMouse>

    <context name="Frame">
      <mousebind button="A-Left" action="Press">
        <action name="Focus"/>
        <action name="Raise"/>
      </mousebind>
      <mousebind button="A-Left" action="Click">
        <action name="Unshade"/>
      </mousebind>
      <mousebind button="A-Left" action="Drag">
        <action name="Move"/>
      </mousebind>
      <mousebind button="A-Right" action="Press">
        <action name="Focus"/>
        <action name="Raise"/>
        <action name="Unshade"/>
      </mousebind>
      <mousebind button="A-Right" action="Drag">
        <action name="Resize"/>
      </mousebind>
      <mousebind button="A-Middle" action="Press">
        <action name="Lower"/>
        <action name="FocusToBottom"/>
        <action name="Unfocus"/>
      </mousebind>
    </context>

    <context name="Titlebar">
      <mousebind button="Left" action="Press">
        <action name="Focus"/>
        <action name="Raise"/>
      </mousebind>
      <mousebind button="Left" action="Drag">
        <action name="Move"/>
      </mousebind>
      <mousebind button="Left" action="DoubleClick">
        <action name="ToggleMaximize"/>
      </mousebind>
      <mousebind button="Middle" action="Press">
        <action name="Lower"/>
        <action name="FocusToBottom"/>
        <action name="Unfocus"/>
      </mousebind>
      <mousebind button="Right" action="Press">
        <action name="Focus"/>
        <action name="Raise"/>
        <action name="ShowMenu">
          <menu>client-menu</menu>
        </action>
      </mousebind>
    </context>

    <context name="Desktop">
      <mousebind button="Up" action="Click">
        <action name="GoToDesktop">
          <to>previous</to>
        </action>
      </mousebind>
      <mousebind button="Down" action="Click">
        <action name="GoToDesktop">
          <to>next</to>
        </action>
      </mousebind>
      <mousebind button="A-Up" action="Click">
        <action name="GoToDesktop">
          <to>previous</to>
        </action>
      </mousebind>
      <mousebind button="A-Down" action="Click">
        <action name="GoToDesktop">
          <to>next</to>
        </action>
      </mousebind>
      <mousebind button="Left" action="Press">
        <action name="Focus"/>
        <action name="Raise"/>
      </mousebind>
      <mousebind button="Right" action="Press">
        <action name="ShowMenu">
          <menu>root-menu</menu>
        </action>
      </mousebind>
    </context>

    <context name="Root">
      <mousebind button="Middle" action="Press">
        <action name="ShowMenu">
          <menu>client-list-combined-menu</menu>
        </action>
      </mousebind>
      <mousebind button="Right" action="Press">
        <action name="ShowMenu">
          <menu>root-menu</menu>
        </action>
      </mousebind>
    </context>
  </mouse>

  <menu>
    <file>menu.xml</file>
    <hideDelay>200</hideDelay>
    <middle>no</middle>
    <submenuShowDelay>100</submenuShowDelay>
    <submenuHideDelay>400</submenuHideDelay>
    <applicationIcons>yes</applicationIcons>
    <manageDesktops>yes</manageDesktops>
  </menu>

  <applications>
    <application name="obconf">
      <decor>yes</decor>
    </application>
  </applications>

</openbox_config>
